LICENSE
README.md
pyproject.toml
setup.cfg
setup.py
src/bob_vf_client.egg-info/PKG-INFO
src/bob_vf_client.egg-info/SOURCES.txt
src/bob_vf_client.egg-info/dependency_links.txt
src/bob_vf_client.egg-info/requires.txt
src/bob_vf_client.egg-info/top_level.txt
src/client/__init__.py
src/client/voxelfarmclient.py