Metadata-Version: 2.1
Name: bob-vf-client
Version: 0.0.2
Summary: A small example package
Home-page: https://www.voxelfarm.com/help/PythonCookbook.html
Author: Roberto Alonso Gomez
Author-email: rag700504@hotmail.com
License: UNKNOWN
Project-URL: Bug Tracker, https://github.com/voxelfarm/voxelfarmclient/issues
Platform: UNKNOWN
Classifier: Programming Language :: Python :: 3
Classifier: License :: OSI Approved :: MIT License
Classifier: Operating System :: OS Independent
Requires-Python: >=3.6
Provides-Extra: dev
License-File: LICENSE
